forkedsubprocess/__init__.py
forkedsubprocess-1.0.3.dist-info/LICENSE
forkedsubprocess-1.0.3.dist-info/METADATA
forkedsubprocess-1.0.3.dist-info/WHEEL
forkedsubprocess-1.0.3.dist-info/top_level.txt
forkedsubprocess-1.0.3.dist-info/RECORD
