Metadata-Version: 2.1
Name: forkedsubprocess
Version: 1.0.3
Summary: Forked subprocess support for Python
Home-page: https://gitlab.devlabs.linuxassist.net/allworldit/python/forkedsubprocess
Author: Nigel Kukard
Author-email: nkukard@lbsd.net
License: UNKNOWN
Platform: UNKNOWN
Classifier: Development Status :: 5 - Production/Stable
Classifier: Intended Audience :: Developers
Classifier: License :: OSI Approved :: MIT License
Classifier: Operating System :: POSIX :: Linux
Classifier: Programming Language :: Python :: 3 :: Only
Classifier: Topic :: Software Development :: Libraries :: Python Modules
Requires-Python: >=3.6
